duo_game_lib/__init__.py
duo_game_lib/game.py
duo_game_lib/game_state.py
duo_game_lib/judge.py
duo_game_lib/move.py
duo_game_lib/player.py
duo_game_lib-0.1.2.dist-info/METADATA
duo_game_lib-0.1.2.dist-info/WHEEL
duo_game_lib-0.1.2.dist-info/RECORD
