Metadata-Version: 2.1
Name: duo-game-lib
Version: 0.1.2
Summary: Logic for turn-based duo game
Author: game-ai-platform-team
Requires-Python: >=3.10,<4.0
Classifier: Programming Language :: Python :: 3
Classifier: Programming Language :: Python :: 3.10
Classifier: Programming Language :: Python :: 3.11
Classifier: Programming Language :: Python :: 3.12
